xarray/__init__.py
xarray/coders.py
xarray/conventions.py
xarray/convert.py
xarray/groupers.py
xarray/py.typed
xarray/tutorial.py
xarray/typing.py
xarray/ufuncs.py
xarray/backends/__init__.py
xarray/backends/api.py
xarray/backends/chunks.py
xarray/backends/common.py
xarray/backends/file_manager.py
xarray/backends/h5netcdf_.py
xarray/backends/locks.py
xarray/backends/lru_cache.py
xarray/backends/memory.py
xarray/backends/netCDF4_.py
xarray/backends/netcdf3.py
xarray/backends/plugins.py
xarray/backends/pydap_.py
xarray/backends/scipy_.py
xarray/backends/store.py
xarray/backends/writers.py
xarray/backends/zarr.py
xarray/coding/__init__.py
xarray/coding/calendar_ops.py
xarray/coding/cftime_offsets.py
xarray/coding/cftimeindex.py
xarray/coding/common.py
xarray/coding/frequencies.py
xarray/coding/strings.py
xarray/coding/times.py
xarray/coding/variables.py
xarray/compat/__init__.py
xarray/compat/array_api_compat.py
xarray/compat/dask_array_compat.py
xarray/compat/dask_array_ops.py
xarray/compat/npcompat.py
xarray/compat/pdcompat.py
xarray/compat/toolzcompat.py
xarray/computation/__init__.py
xarray/computation/apply_ufunc.py
xarray/computation/arithmetic.py
xarray/computation/computation.py
xarray/computation/fit.py
xarray/computation/nanops.py
xarray/computation/ops.py
xarray/computation/rolling.py
xarray/computation/rolling_exp.py
xarray/computation/weighted.py
xarray/core/__init__.py
xarray/core/_aggregations.py
xarray/core/_typed_ops.py
xarray/core/accessor_dt.py
xarray/core/accessor_str.py
xarray/core/common.py
xarray/core/coordinate_transform.py
xarray/core/coordinates.py
xarray/core/dataarray.py
xarray/core/dataset.py
xarray/core/dataset_utils.py
xarray/core/dataset_variables.py
xarray/core/datatree.py
xarray/core/datatree_mapping.py
xarray/core/datatree_render.py
xarray/core/dtypes.py
xarray/core/duck_array_ops.py
xarray/core/extension_array.py
xarray/core/extensions.py
xarray/core/formatting.py
xarray/core/formatting_html.py
xarray/core/groupby.py
xarray-2025.10.0.dist-info/licenses/LICENSE
xarray-2025.10.0.dist-info/METADATA
xarray-2025.10.0.dist-info/WHEEL
xarray-2025.10.0.dist-info/entry_points.txt
xarray-2025.10.0.dist-info/top_level.txt
xarray-2025.10.0.dist-info/RECORD
