Metadata-Version: 2.4
Name: xarray
Version: 2025.10.0
Summary: N-D labeled arrays and datasets in Python
Author-email: xarray Developers <xarray@googlegroups.com>
License-Expression: Apache-2.0
Project-URL: Documentation, https://docs.xarray.dev
Project-URL: SciPy2015-talk, https://www.youtube.com/watch?v=X0pAhJgySxk
Project-URL: homepage, https://xarray.dev/
Project-URL: issue-tracker, https://github.com/pydata/xarray/issues
Project-URL: source-code, https://github.com/pydata/xarray
Classifier: Development Status :: 5 - Production/Stable
Classifier: Operating System :: OS Independent
Classifier: Intended Audience :: Science/Research
Classifier: Programming Language :: Python
Classifier: Programming Language :: Python :: 3
Classifier: Programming Language :: Python :: 3.11
Classifier: Programming Language :: Python :: 3.12
Classifier: Programming Language :: Python :: 3.13
Classifier: Topic :: Scientific/Engineering
Requires-Python: >=3.11
License-File: LICENSE
Requires-Dist: numpy>=1.26
Requires-Dist: packaging>=24.1
Requires-Dist: pandas>=2.2
Provides-Extra: accel
Requires-Dist: scipy>=1.13; extra == "accel"
Requires-Dist: bottleneck; extra == "accel"
Requires-Dist: numbagg>=0.8; extra == "accel"
Requires-Dist: numba>=0.62; extra == "accel"
Requires-Dist: flox>=0.9; extra == "accel"
Requires-Dist: opt_einsum; extra == "accel"
Provides-Extra: complete
Requires-Dist: xarray[accel,etc,io,parallel,viz]; extra == "complete"
Provides-Extra: io
Requires-Dist: netCDF4>=1.6.0; extra == "io"
Requires-Dist: h5netcdf; extra == "io"
Requires-Dist: pydap; extra == "io"
Requires-Dist: scipy>=1.13; extra == "io"
Requires-Dist: zarr>=2.18; extra == "io"
Requires-Dist: fsspec; extra == "io"
Requires-Dist: cftime; extra == "io"
Requires-Dist: pooch; extra == "io"
Provides-Extra: etc
Requires-Dist: sparse>=0.15; extra == "etc"
Provides-Extra: parallel
Requires-Dist: dask[complete]; extra == "parallel"
Provides-Extra: viz
Requires-Dist: cartopy>=0.23; extra == "viz"
Requires-Dist: matplotlib; extra == "viz"
Requires-Dist: nc-time-axis; extra == "viz"
Requires-Dist: seaborn; extra == "viz"
Provides-Extra: types
Requires-Dist: pandas-stubs; extra == "types"
Requires-Dist: scipy-stubs; extra == "types"
Requires-Dist: types-PyYAML; extra == "types"
Requires-Dist: types-Pygments; extra == "types"
Requires-Dist: types-colorama; extra == "types"
Requires-Dist: types-decorator; extra == "types"
Requires-Dist: types-defusedxml; extra == "types"
Requires-Dist: types-docutils; extra == "types"
Requires-Dist: types-networkx; extra == "types"
Requires-Dist: types-pexpect; extra == "types"
Requires-Dist: types-psutil; extra == "types"
Requires-Dist: types-pycurl; extra == "types"
Requires-Dist: types-openpyxl; extra == "types"
Requires-Dist: types-python-dateutil; extra == "types"
Requires-Dist: types-pytz; extra == "types"
Requires-Dist: types-requests; extra == "types"
Requires-Dist: types-setuptools; extra == "types"
Dynamic: license-file
